proxyframe/__init__.py
proxyframe/clonning.py
proxyframe-0.0.1.dist-info/METADATA
proxyframe-0.0.1.dist-info/WHEEL
proxyframe-0.0.1.dist-info/top_level.txt
proxyframe-0.0.1.dist-info/RECORD
